{
  "id": "istok-web",
  "family": "Istok Web",
  "subsets": ["cyrillic", "cyrillic-ext", "latin", "latin-ext"],
  "weights": [400, 700],
  "styles": ["italic", "normal"],
  "defSubset": "latin",
  "variable": false,
  "lastModified": "2023-08-25",
  "version": "v24",
  "category": "sans-serif",
  "license": {
    "type": "OFL-1.1",
    "url": "http://scripts.sil.org/OFL",
    "attribution": "Copyright (c) 2008-2014, Andrey V. Panov (panov@canopus.iacp.dvo.ru), with Reserved Font Name Istok"
  },
  "source": "https://github.com/google/fonts",
  "type": "google"
}