{
  "id": "corben",
  "family": "Corben",
  "subsets": ["latin", "latin-ext"],
  "weights": [400, 700],
  "styles": ["normal"],
  "defSubset": "latin",
  "variable": false,
  "lastModified": "2025-09-10",
  "version": "v23",
  "category": "display",
  "license": {
    "type": "OFL-1.1",
    "url": "https://openfontlicense.org",
    "attribution": "Copyright (c) 2010, 2011 by vernon adams (vern@newtypography.co.uk) with Reserved Font Name 'Corben'. Corben-Bold.ttf: Copyright (c) 2010, 2011 by vernon adams (vern@newtypography.co.uk) with Reserved Font Name 'Corben'. All rights reserved."
  },
  "source": "https://github.com/google/fonts",
  "type": "google"
}