{
  "id": "rammetto-one",
  "family": "Rammetto One",
  "subsets": ["latin", "latin-ext"],
  "weights": [400],
  "styles": ["normal"],
  "defSubset": "latin",
  "variable": false,
  "lastModified": "2024-09-04",
  "version": "v19",
  "category": "display",
  "license": {
    "type": "OFL-1.1",
    "url": "https://openfontlicense.org",
    "attribution": "Copyright 2011 The Rammetto Project Authors (https://github.com/googlefonts/RammettoFont), with Reserved Font Name Rammetto."
  },
  "source": "https://github.com/google/fonts",
  "type": "google"
}