{
  "id": "noto-sans-old-turkic",
  "family": "Noto Sans Old Turkic",
  "subsets": ["latin", "latin-ext", "old-turkic"],
  "weights": [400],
  "styles": ["normal"],
  "defSubset": "latin",
  "variable": false,
  "lastModified": "2024-07-30",
  "version": "v18",
  "category": "sans-serif",
  "license": {
    "type": "OFL-1.1",
    "url": "https://openfontlicense.org",
    "attribution": "Copyright 2022 The Noto Project Authors (https://github.com/notofonts/old-turkic)"
  },
  "source": "https://github.com/google/fonts",
  "type": "google"
}